toulouse/__init__.py
toulouse/core.py
toulouse-1.0.1.dist-info/licenses/LICENSE
toulouse-1.0.1.dist-info/METADATA
toulouse-1.0.1.dist-info/WHEEL
toulouse-1.0.1.dist-info/top_level.txt
toulouse-1.0.1.dist-info/RECORD
