Metadata-Version: 2.4
Name: toulouse
Version: 1.0.1
Summary: High-performance card library for ML and RL applications.
Author: mlabarrere
Author-email: Your Name <your.email@example.com>
License-Expression: MIT
Project-URL: Homepage, https://github.com/yourusername/toulouse
Project-URL: Repository, https://github.com/yourusername/toulouse
Project-URL: Documentation, https://github.com/yourusername/toulouse#readme
Project-URL: Bug Tracker, https://github.com/yourusername/toulouse/issues
Keywords: cards,game,reinforcement-learning,mcts,numpy
Classifier: Development Status :: 4 - Beta
Classifier: Intended Audience :: Developers
Classifier: Programming Language :: Python :: 3
Classifier: Programming Language :: Python :: 3.9
Classifier: Programming Language :: Python :: 3.10
Classifier: Programming Language :: Python :: 3.11
Classifier: Programming Language :: Python :: 3.12
Classifier: Topic :: Games/Entertainment
Classifier: Topic :: Scientific/Engineering :: Artificial Intelligence
Requires-Python: >=3.9
License-File: LICENSE
Requires-Dist: build>=1.2.2.post1
Requires-Dist: numpy>=1.20
Dynamic: license-file
